dlake/__init__.py
dlake/auth.py
dlake/chain.pravah.io.crt
dlake/dlake.py
dlake-0.1.8.dist-info/METADATA
dlake-0.1.8.dist-info/WHEEL
dlake-0.1.8.dist-info/top_level.txt
dlake-0.1.8.dist-info/RECORD
