Metadata-Version: 2.1
Name: dlake
Version: 0.1.8
Summary: Dynamic timer to learn the update frequency of a resource on the web
Home-page: https://github.com/upperwal
Author: Abhishek Upperwal
Author-email: mesh@soket.in
License: UNKNOWN
Platform: UNKNOWN
Classifier: Programming Language :: Python :: 3
Classifier: License :: OSI Approved :: MIT License
Classifier: Operating System :: OS Independent
Requires-Dist: pymongo
Requires-Dist: requests
Requires-Dist: datetime
